README.md
setup.cfg
setup.py
cp2130/__init__.py
cp2130/clock.py
cp2130/core.py
cp2130/event_counter.py
cp2130/gpio.py
cp2130/pin_config.py
cp2130/spi.py
cp2130/usb_config.py
cp2130.egg-info/PKG-INFO
cp2130.egg-info/SOURCES.txt
cp2130.egg-info/dependency_links.txt
cp2130.egg-info/not-zip-safe
cp2130.egg-info/requires.txt
cp2130.egg-info/top_level.txt
cp2130/_utils/__init__.py
cp2130/_utils/bcd.py
cp2130/chip/__init__.py
cp2130/chip/base.py
cp2130/chip/chip.py
cp2130/chip/commands.py
cp2130/chip/fields.py
cp2130/chip/registers.py
cp2130/data/__init__.py
cp2130/data/event_counter.py
cp2130/data/gpio.py
cp2130/data/rom.py
cp2130/data/spi.py
cp2130/data/usb.py
cp2130/usb/__init__.py
cp2130/usb/pyusb.py
cp2130/usb/usb.py
cp2130/usb/libusb1/__init__.py
cp2130/usb/libusb1/core.py
cp2130/usb/libusb1/hotplug.py