Metadata-Version: 1.1
Name: cp2130
Version: 1.1.1
Summary: Library for the Silicon Labs CP2130 USB to SPI Bridge
Home-page: https://github.com/drbild/cp2130
Author: David R. Bild
Author-email: david@davidbild.org
License: Apache 2.0
Download-URL: https://github.com/drbild/cp2130/archive/1.1.1.tar.gz
Keywords: usb,spi,bridge,Silicon Labs,silabs,cp2130,cp213x
Platform: UNKNOWN
Classifier: Development Status :: 5 - Production/Stable
Classifier: Intended Audience :: Developers
Classifier: License :: OSI Approved :: Apache Software License
Classifier: Programming Language :: Python
Classifier: Programming Language :: Python :: 2
Classifier: Programming Language :: Python :: 2.7
Classifier: Programming Language :: Python :: 3
Classifier: Programming Language :: Python :: 3.4
Classifier: Programming Language :: Python :: 3.5
Classifier: Programming Language :: Python :: 3.6
Classifier: Programming Language :: Python :: Implementation :: CPython
Classifier: Operating System :: POSIX
Classifier: Operating System :: Unix
Classifier: Operating System :: MacOS
Classifier: Operating System :: Microsoft
